vqf/__init__.py
vqf/__init__.pyi
vqf/basicvqf.cp313-win32.pyd
vqf/basicvqf.pyi
vqf/pyvqf.py
vqf/utils.py
vqf/vqf.cp313-win32.pyd
vqf/vqf.pyi
vqf/cpp/CMakeLists.txt
vqf/cpp/basicvqf.cpp
vqf/cpp/basicvqf.hpp
vqf/cpp/offline_vqf.cpp
vqf/cpp/offline_vqf.hpp
vqf/cpp/vqf.cpp
vqf/cpp/vqf.hpp
vqf/matlab/VQF.m
vqf-2.1.0.dist-info/METADATA
vqf-2.1.0.dist-info/WHEEL
vqf-2.1.0.dist-info/top_level.txt
vqf-2.1.0.dist-info/RECORD
