Metadata-Version: 2.4
Name: vqf
Version: 2.1.0
Summary: A Versatile Quaternion-based Filter for IMU Orientation Estimation
Home-page: https://github.com/dlaidig/vqf/
Author: Daniel Laidig
Author-email: laidig@control.tu-berlin.de
License: MIT
Project-URL: Documentation, https://vqf.readthedocs.io/
Classifier: Development Status :: 5 - Production/Stable
Classifier: Intended Audience :: Science/Research
Classifier: License :: OSI Approved :: MIT License
Classifier: Programming Language :: Python :: 3
Requires-Python: >=3.10
Requires-Dist: numpy>=1.20.0
Provides-Extra: dev
Requires-Dist: tox; extra == "dev"
Requires-Dist: pytest; extra == "dev"
Requires-Dist: flake8; extra == "dev"
Requires-Dist: reuse; extra == "dev"
Requires-Dist: transplant; extra == "dev"
Requires-Dist: oct2py; extra == "dev"
Requires-Dist: scipy; extra == "dev"
Requires-Dist: breathe; extra == "dev"
Requires-Dist: matplotlib; extra == "dev"
Requires-Dist: sphinx; extra == "dev"
Requires-Dist: sphinx-rtd-theme; extra == "dev"
Requires-Dist: sphinxcontrib-matlabdomain; extra == "dev"
Dynamic: author
Dynamic: author-email
Dynamic: classifier
Dynamic: description
Dynamic: description-content-type
Dynamic: home-page
Dynamic: license
Dynamic: project-url
Dynamic: provides-extra
Dynamic: requires-dist
Dynamic: requires-python
Dynamic: summary
